{"packages/cupertino_icons/assets/CupertinoIcons.ttf":["packages/cupertino_icons/assets/CupertinoIcons.ttf"],"lib/res/drawables/bg1.jpg":["lib/res/drawables/bg1.jpg"],"lib/res/drawables/github.webp":["lib/res/drawables/github.webp"],"lib/res/drawables/google_play.webp":["lib/res/drawables/google_play.webp"],"lib/res/drawables/instagram.webp":["lib/res/drawables/instagram.webp"],"lib/res/drawables/linkedin.webp":["lib/res/drawables/linkedin.webp"],"lib/res/drawables/stackoverflow.webp":["lib/res/drawables/stackoverflow.webp"]}